simplefetch/__init__.py
simplefetch-0.1.0.dist-info/LICENSE.md
simplefetch-0.1.0.dist-info/METADATA
simplefetch-0.1.0.dist-info/WHEEL
simplefetch-0.1.0.dist-info/top_level.txt
simplefetch-0.1.0.dist-info/RECORD
