Metadata-Version: 2.1
Name: simplefetch
Version: 0.1.0
Summary: Simplified Paramiko Library to Fetch Data From MultiVendor Network Devices
Home-page: https://github.com/ercintorun/simplefetch
Author: Ercin TORUN
Author-email: ercintorun@gmail.com
License: UNKNOWN
Platform: UNKNOWN
Classifier: Programming Language :: Python :: 3
Classifier: License :: OSI Approved :: MIT License
Classifier: Operating System :: OS Independent
Requires-Python: >=3.6
